test_pypi/__init__.py
test_pypi/cool.py
test_casadi_pypi-1.0.1.dist-info/METADATA
test_casadi_pypi-1.0.1.dist-info/WHEEL
test_casadi_pypi-1.0.1.dist-info/top_level.txt
test_casadi_pypi-1.0.1.dist-info/RECORD
