Metadata-Version: 2.1
Name: test_casadi_pypi
Version: 1.0.1
Summary: Comma webRTC abstractions
Author-email: Vehicle Researcher <user@comma.ai>
Classifier: Programming Language :: Python :: 3
Classifier: License :: OSI Approved :: MIT License
Classifier: Operating System :: OS Independent
Requires-Python: >=3.8
Requires-Dist: numpy >=1.19.0
